{
    "type": "crafting_shaped",
    "category": "misc",
    "pattern": [
        "RBR",
        "BDB",
        "RBR"
    ],
    "key": {
        "R": "redstone",
        "B": "book",
        "D": "diamond"
    },
    "result": {
        "id": "written_book",
        "count": 1,
        "components": {
            "written_book_content": {
                "title": "Книга Рун",
                "author": "NekoCraft",
                "generation": 0,
                "pages": [
                    '[
                        [
                            {
                                "text": "Используйте с умом, Книга одноразовая.\n"
                            },
                            {
                                "text": "[СБРОС ЭФФЕКТА]\n",
                                "clickEvent": {
                                    "action": "run_command",
                                    "value": "/trigger ncb.rune set -1"
                                }
                            },
                            {
                                "text": "2+ Уровень: \n"
                            },
                            {
                                "text": "[Сердца]\n",
                                "clickEvent": {
                                    "action": "run_command",
                                    "value": "/trigger ncb.rune set 1"
                                }
                            },
                            {
                                "text": "[Листва Вишни]\n",
                                "clickEvent": {
                                    "action": "run_command",
                                    "value": "/trigger ncb.rune set 2"
                                }
                            },
                            {
                                "text": "[Дым]\n",
                                "clickEvent": {
                                    "action": "run_command",
                                    "value": "/trigger ncb.rune set 3"
                                }
                            },
                            {
                                "text": "[Пламя]\n",
                                "clickEvent": {
                                    "action": "run_command",
                                    "value": "/trigger ncb.rune set 4"
                                }
                            },
                            {
                                "text": "[Дождь]\n",
                                "clickEvent": {
                                    "action": "run_command",
                                    "value": "/trigger ncb.rune set 5"
                                }
                            },
                            {
                                "text": "[Чернила]\n",
                                "clickEvent": {
                                    "action": "run_command",
                                    "value": "/trigger ncb.rune set 6"
                                }
                            },
                            {
                                "text": "[Снежинки]\n",
                                "clickEvent": {
                                    "action": "run_command",
                                    "value": "/trigger ncb.rune set 7"
                                }
                            },
                            {
                                "text": "[Слизь]\n",
                                "clickEvent": {
                                    "action": "run_command",
                                    "value": "/trigger ncb.rune set 8"
                                }
                            },
                            {
                                "text": "[Серая Листва]\n",
                                "clickEvent": {
                                    "action": "run_command",
                                    "value": "/trigger ncb.rune set 9"
                                }
                            }
                        ]
                    ]',
                    '[
                        [
                            [
                                {
                                    "text": "3+ Уровень: \n"
                                },
                                {
                                    "text": "[Ноты]\n",
                                    "clickEvent": {
                                        "action": "run_command",
                                        "value": "/trigger ncb.rune set 10"
                                    }
                                }
                            ]
                        ]
                    ]'
                ]
            },
            "custom_data": {
                "BoosterBook": 2
            }
        }
    }
}
